caspass/__init__.py
caspass/utils.py
python_caspass-0.1.2.dist-info/COPYING
python_caspass-0.1.2.dist-info/METADATA
python_caspass-0.1.2.dist-info/WHEEL
python_caspass-0.1.2.dist-info/RECORD
