Metadata-Version: 2.1
Name: python-caspass
Version: 0.1.2
Summary: CASPass - Login through Central Authentification Systems
Home-page: https://codeberg.org/oschwand/python-caspass
Author: Olivier Schwander
Author-email: olivier.schwander@chadok.info
Requires-Python: >=3.11,<4.0
Classifier: Programming Language :: Python :: 3
Classifier: Programming Language :: Python :: 3.11
Provides-Extra: examples
Requires-Dist: bs4 (>=0.0.2,<0.0.3) ; extra == "examples"
Requires-Dist: httpx (>=0.26.0,<0.27.0) ; extra == "examples"
Requires-Dist: playwright (>=1.32.1,<2.0.0)
Requires-Dist: python-decouple (>=3.8,<4.0) ; extra == "examples"
